flask_mail_sendgrid.py
setup.py
Flask_Mail_SendGrid.egg-info/PKG-INFO
Flask_Mail_SendGrid.egg-info/SOURCES.txt
Flask_Mail_SendGrid.egg-info/dependency_links.txt
Flask_Mail_SendGrid.egg-info/requires.txt
Flask_Mail_SendGrid.egg-info/top_level.txt