Metadata-Version: 1.1
Name: Flask-Mail-SendGrid
Version: 0.1.1
Summary: Flask extension for sendgrid. It has same interface with Flask-Mail.
Home-page: http://github.com/hamano/flask-mail-sendgrid
Author: HAMANO Tsukasa
Author-email: code@cuspy.org
License: MIT
Platform: UNKNOWN
Classifier: Development Status :: 4 - Beta
Classifier: Environment :: Web Environment
Classifier: Intended Audience :: Developers
Classifier: Operating System :: OS Independent
Classifier: License :: OSI Approved :: MIT License
Classifier: Programming Language :: Python
Classifier: Topic :: Internet :: WWW/HTTP :: Dynamic Content
Classifier: Topic :: Software Development :: Libraries :: Python Modules
